[
    {
        "ingredientPattern": "A,L",
        "recipeGroup": 2,
        "ingredients": {
            "A": {
                "type": "item",
                "code": "rhadditions:armor-head-found-elvish-leather"
            },
            "L": {
                "type": "item",
                "code": "game:leather-green"
            }
        },
        "width": 1,
        "height": 2,
        "shapeless": true,
        "copyAttributesFrom": "A",
        "averageDurability": false,
        "name": "elvish leather helmet repair",
        "output": {
            "type": "item",
            "code": "rhadditions:armor-head-found-elvish-leather"
        }
    },
    {
        "ingredientPattern": "A,L",
        "recipeGroup": 2,
        "ingredients": {
            "A": {
                "type": "item",
                "code": "rhadditions:armor-body-found-elvish-leather"
            },
            "L": {
                "type": "item",
                "code": "game:leather-green"
            }
        },
        "width": 1,
        "height": 2,
        "shapeless": true,
        "copyAttributesFrom": "A",
        "averageDurability": false,
        "name": "elvish leather body armor repair",
        "output": {
            "type": "item",
            "code": "rhadditions:armor-body-found-elvish-leather"
        }
    },
    {
        "ingredientPattern": "A,L",
        "recipeGroup": 2,
        "ingredients": {
            "A": {
                "type": "item",
                "code": "rhadditions:armor-legs-found-elvish-leather"
            },
            "L": {
                "type": "item",
                "code": "game:leather-green"
            }
        },
        "width": 1,
        "height": 2,
        "shapeless": true,
        "copyAttributesFrom": "A",
        "averageDurability": false,
        "name": "elvish leather leg armor repair",
        "output": {
            "type": "item",
            "code": "rhadditions:armor-legs-found-elvish-leather"
        }
    }
]